hugg/__init__.py
hugg-0.2.67.dist-info/LICENSE
hugg-0.2.67.dist-info/METADATA
hugg-0.2.67.dist-info/WHEEL
hugg-0.2.67.dist-info/top_level.txt
hugg-0.2.67.dist-info/RECORD
