Metadata-Version: 2.1
Name: hugg
Version: 0.2.67
Summary: My short description for my project.
Home-page: https://github.com/franceme/hugg
Author: Miles Frantz
Author-email: frantzme@vt.edu
Classifier: Programming Language :: Python
Classifier: Programming Language :: Python :: 3
Classifier: Programming Language :: Python :: 3.8
Requires-Python: >=3.8.0
License-File: LICENSE
Requires-Dist: ephfile
Requires-Dist: mystring
Requires-Dist: fs
Provides-Extra: all
Requires-Dist: splych ; extra == 'all'
Requires-Dist: PyGithub ; extra == 'all'
Requires-Dist: requests ; extra == 'all'
Requires-Dist: gett ; extra == 'all'
Requires-Dist: mystring ; extra == 'all'
Requires-Dist: waybackpy ; extra == 'all'
Requires-Dist: git4net ; extra == 'all'
Requires-Dist: splittr ; extra == 'all'
Requires-Dist: python-gitlab ; extra == 'all'
Requires-Dist: ruamel.std.zipfile ; extra == 'all'
Requires-Dist: huggingface-hub ; extra == 'all'
Requires-Dist: datasets ; extra == 'all'
Requires-Dist: pandas ; extra == 'all'
Requires-Dist: openpyxl ; extra == 'all'
Requires-Dist: pydbhub ; extra == 'all'
Requires-Dist: docker ; extra == 'all'
Requires-Dist: ephfile ; extra == 'all'
Provides-Extra: dbhub
Requires-Dist: huggingface-hub ; extra == 'dbhub'
Requires-Dist: datasets ; extra == 'dbhub'
Requires-Dist: pydbhub ; extra == 'dbhub'
Provides-Extra: docker
Requires-Dist: docker ; extra == 'docker'
Requires-Dist: ephfile ; extra == 'docker'
Provides-Extra: excel
Requires-Dist: huggingface-hub ; extra == 'excel'
Requires-Dist: datasets ; extra == 'excel'
Requires-Dist: openpyxl ; extra == 'excel'
Provides-Extra: face
Requires-Dist: huggingface-hub ; extra == 'face'
Requires-Dist: datasets ; extra == 'face'
Provides-Extra: ghub
Requires-Dist: PyGithub ; extra == 'ghub'
Requires-Dist: requests ; extra == 'ghub'
Requires-Dist: gett ; extra == 'ghub'
Requires-Dist: mystring ; extra == 'ghub'
Provides-Extra: glab
Requires-Dist: python-gitlab ; extra == 'glab'
Provides-Extra: q_ghub
Requires-Dist: PyGithub ; extra == 'q_ghub'
Requires-Dist: requests ; extra == 'q_ghub'
Requires-Dist: gett ; extra == 'q_ghub'
Requires-Dist: waybackpy ; extra == 'q_ghub'
Requires-Dist: git4net ; extra == 'q_ghub'
Requires-Dist: splittr ; extra == 'q_ghub'
Provides-Extra: splych
Requires-Dist: splych ; extra == 'splych'
Provides-Extra: sqlite
Requires-Dist: mystring ; extra == 'sqlite'
Requires-Dist: pandas ; extra == 'sqlite'
Provides-Extra: zip
Requires-Dist: ruamel.std.zipfile ; extra == 'zip'
